{"reads": [
	{
		"id": 1,
		"PosiSol_V": [
			{
				"X_V": 0.46, 
				"Y_V": -0.23,
				"Z_V": -0.57
			}
		]
	},
	{
		"id": 2,
		"PosiSol_V": [
			{
				"X_V": 0.46, 
				"Y_V": -0.23,
				"Z_V": -0.57
			}
		]
	},
	{
		"id": 3,
		"PosiSol_V": [
			{
				"X_V": 0.46, 
				"Y_V": -0.23,
				"Z_V": -0.57
			}
		]
	},
	{
		"id": 4,
		"PosiSol_V": [
			{
				"X_V": 0.46, 
				"Y_V": -0.23,
				"Z_V": -0.57
			}
		]
	},
	{
		"id": 5,
		"PosiSol_V": [
			{
				"X_V": 0.46, 
				"Y_V": -0.23,
				"Z_V": -0.57
			}
		]
	}
]}